LICENSE
MANIFEST.in
README.md
setup.py
django_psycopg2_extension.egg-info/PKG-INFO
django_psycopg2_extension.egg-info/SOURCES.txt
django_psycopg2_extension.egg-info/dependency_links.txt
django_psycopg2_extension.egg-info/not-zip-safe
django_psycopg2_extension.egg-info/requires.txt
django_psycopg2_extension.egg-info/top_level.txt
psycopg2_extension/__init__.py
psycopg2_extension/base_command.py
psycopg2_extension/patch_database_creation.py
psycopg2_extension/utils.py
psycopg2_extension/management/__init__.py
psycopg2_extension/management/commands/__init__.py
psycopg2_extension/management/commands/psqlclean.py
psycopg2_extension/management/commands/psqlinit.py
psycopg2_extension/management/commands/psqlsnapshot.py
psycopg2_extension/management/commands/psqlviews.py