Metadata-Version: 2.1
Name: django-psycopg2-extension
Version: 0.2.0
Summary: Library contains django commands which helps to prepare and manage PostgreSQL database.
Home-page: https://github.com/druids/django-psycopg2-extension
Author: Lubos Matl
Author-email: matllubos@gmail.com
License: MIT
Classifier: Development Status :: 3 - Alpha
Classifier: Framework :: Django
Classifier: Intended Audience :: Developers
Classifier: License :: OSI Approved :: BSD License
Classifier: Operating System :: OS Independent
Classifier: Programming Language :: Python
Classifier: Topic :: Internet :: WWW/HTTP
License-File: LICENSE
